ironfence/__init__.py
ironfence/py.typed
ironfence-0.1.0.dist-info/METADATA
ironfence-0.1.0.dist-info/WHEEL
ironfence-0.1.0.dist-info/licenses/LICENSE
ironfence-0.1.0.dist-info/RECORD
