Metadata-Version: 2.1
Name: ironfence
Version: 0.1.0
Summary: Synchronization primitives specifically designed for use with Asyncio Coroutines, inspired by Rust.
Project-URL: repository, https://github.com/ab0142/ironfence
Author-email: ab0142 <120799552+ab0142@users.noreply.github.com>
License-File: LICENSE
Keywords: asyncio,mutex,rust,rwlock,synchronization
Classifier: Development Status :: 4 - Beta
Classifier: Environment :: Console
Classifier: Framework :: AsyncIO
Classifier: Framework :: Hatch
Classifier: Intended Audience :: Developers
Classifier: License :: OSI Approved :: MIT License
Classifier: Programming Language :: Python :: 3.8
Classifier: Programming Language :: Python :: 3.9
Classifier: Programming Language :: Python :: 3.10
Classifier: Programming Language :: Python :: 3.11
Classifier: Programming Language :: Python :: Implementation :: PyPy
Classifier: Topic :: Software Development :: Libraries :: Python Modules
Classifier: Typing :: Typed
Requires-Python: >=3.8
Requires-Dist: aiorwlock~=1.3.0
Provides-Extra: dev
Requires-Dist: black~=23.7.0; extra == 'dev'
Requires-Dist: isort~=5.12.0; extra == 'dev'
Requires-Dist: mypy~=1.5.1; extra == 'dev'
Requires-Dist: pre-commit~=3.4.0; extra == 'dev'
Requires-Dist: ruff~=0.0.285; extra == 'dev'
